victordb/__init__.py
victordb/victor.py
victordb-1.0.1.dist-info/METADATA
victordb-1.0.1.dist-info/WHEEL
victordb-1.0.1.dist-info/top_level.txt
victordb-1.0.1.dist-info/RECORD
