Metadata-Version: 2.4
Name: victordb
Version: 1.0.1
Summary: VictorDB is a Python client and ORM for high-performance vector and key-value databases. It provides a simple, flexible API for vector search, key-value storage, and object modeling, making it easy to build modern AI and data applications.
Author-email: Emiliano Billi <emiliano.billi@gmail.com>
Keywords: vector database,key-value,orm,python,database,VictorDB
Classifier: Programming Language :: Python :: 3
Classifier: Operating System :: OS Independent
Classifier: Intended Audience :: Developers
Classifier: Topic :: Database
Classifier: Topic :: Software Development :: Libraries :: Python Modules
Requires-Python: >=3.8
Requires-Dist: cbor2
Requires-Dist: snowflake-id
